<?xml version='1.0' encoding='UTF-8'?>
<Document>
  <Header>
    <SchemaName>Location</SchemaName>
    <Identifier>location_geonames_2755601</Identifier>
    <DocumentState>public</DocumentState>
    <TimeStamp>1390753461781</TimeStamp>
    <SummaryFields>
      <Title>NL &gt; North Brabant &gt; Genderen</Title>
    </SummaryFields>
  </Header>
  <Body>
    <Location>
      <GeopoliticalHierarchy>NL,North Brabant,Genderen</GeopoliticalHierarchy>
      <LocationName>
        <Appelation>Genderen</Appelation>
        <LocationNameType>populated place</LocationNameType>
        <Comments></Comments>
      </LocationName>
      <Coordinates>
        <Longitude>5.0875</Longitude>
        <Latitude>51.73583</Latitude>
      </Coordinates>
      <GeonamesURI>http://www.geonames.org/2755601</GeonamesURI>
      <WikipediaLink/>
      <DbpediaLink/>
    </Location>
  </Body>
</Document>
